pypoi/__init__.py
pypoi/gui.py
pypoi/image_managers.py
pypoi/poissonblending.py
pypoi/util.py
pypoi/testimages/__init__.py
pypoi/testimages/config.py
pypoi/testimages/test1_mask.png
pypoi/testimages/test1_ret.png
pypoi/testimages/test1_src.png
pypoi/testimages/test1_target.png
pypoi/testimages/test2_mask.png
pypoi/testimages/test2_src.png
pypoi/testimages/test2_target.png
pypoi/testimages/test3_mask.png
pypoi/testimages/test3_src.png
pypoi/testimages/test3_target.png
pypoi/testimages/test4_mask.png
pypoi/testimages/test4_src.png
pypoi/testimages/test4_target.png
pypoi-0.3.2.dist-info/LICENSE
pypoi-0.3.2.dist-info/METADATA
pypoi-0.3.2.dist-info/WHEEL
pypoi-0.3.2.dist-info/entry_points.txt
pypoi-0.3.2.dist-info/top_level.txt
pypoi-0.3.2.dist-info/RECORD
