Metadata-Version: 2.1
Name: pypoi
Version: 0.3.2
Summary: "Py"thon program for "Poi"sson Image Editing
Home-page: https://github.com/fbessho/PyPoi
Author: Fumihiro Bessho (Ben)
Author-email: fumihiro.bessho@gmail.com
License: Apache License 2.0
Platform: UNKNOWN
Classifier: Development Status :: 3 - Alpha
Classifier: Environment :: MacOS X
Classifier: Environment :: Win32 (MS Windows)
Classifier: License :: OSI Approved :: Apache Software License
Classifier: Programming Language :: Python :: 2.7
Classifier: Programming Language :: Python :: 3
Requires-Dist: Pillow
Requires-Dist: numpy
Requires-Dist: pyamg
Requires-Dist: scipy
Requires-Dist: future
